fredo/__init__.py
fredo/conf.py
fredo/core.py
fredo/main.py
fredo/fredo_types/__init__.py
fredo/fredo_types/item.py
fredo/gui/__init__.py
fredo/gui/gui.py
fredo/plugins/__init__.py
fredo/plugins/apps.py
fredo/plugins/base.py
fredo/plugins/calculator.py
fredo/plugins/files.py
fredo/plugins/search.py
fredo/plugins/utils.py
fredo-0.0.2.dist-info/LICENSE
fredo-0.0.2.dist-info/METADATA
fredo-0.0.2.dist-info/WHEEL
fredo-0.0.2.dist-info/entry_points.txt
fredo-0.0.2.dist-info/top_level.txt
fredo-0.0.2.dist-info/RECORD
