Metadata-Version: 2.1
Name: fredo
Version: 0.0.2
Summary: Alfred alternative for linux
Home-page: https://gitlab.com/thales-maciel-personal-projecs/alfredo
Author: Thales Maciel
Author-email: thales@thalesmaciel.com
License: MIT
Platform: UNKNOWN
Classifier: License :: OSI Approved :: MIT License
Classifier: Programming Language :: Python :: 3
Classifier: Programming Language :: Python :: 3 :: Only
Classifier: Programming Language :: Python :: 3.6
Classifier: Programming Language :: Python :: 3.7
Classifier: Programming Language :: Python :: 3.8
Requires-Python: >=3.6.1
Requires-Dist: kivymd
